with_cloud_blob/__init__.py
with_cloud_blob/_cli.py
with_cloud_blob/_crypto.py
with_cloud_blob/_log.py
with_cloud_blob/backend_intf.py
with_cloud_blob/crypto_schemas.json
with_cloud_blob/backends/__init__.py
with_cloud_blob/backends/_boto_helpers.py
with_cloud_blob/backends/lock_dynamodb.py
with_cloud_blob/backends/lock_file.py
with_cloud_blob/backends/storage_file.py
with_cloud_blob/backends/storage_s3.py
with_cloud_blob-0.4.4.dist-info/LICENSE
with_cloud_blob-0.4.4.dist-info/METADATA
with_cloud_blob-0.4.4.dist-info/WHEEL
with_cloud_blob-0.4.4.dist-info/entry_points.txt
with_cloud_blob-0.4.4.dist-info/top_level.txt
with_cloud_blob-0.4.4.dist-info/RECORD
