Metadata-Version: 2.1
Name: with-cloud-blob
Version: 0.4.4
Summary: UNKNOWN
Home-page: https://github.com/kshpytsya/with-cloud-blob
Author: Kyrylo Shpytsya
Author-email: kshpitsa@gmail.com
License: MIT
Platform: UNKNOWN
Classifier: Development Status :: 4 - Beta
Classifier: Intended Audience :: Developers
Classifier: Intended Audience :: Information Technology
Classifier: Intended Audience :: System Administrators
Classifier: License :: OSI Approved :: MIT License
Classifier: Operating System :: POSIX
Classifier: Programming Language :: Python :: 3.7
Classifier: Programming Language :: Python :: 3.8
Classifier: Topic :: Security :: Cryptography
Classifier: Topic :: System :: Installation/Setup
Classifier: Topic :: System :: Software Distribution
Classifier: Topic :: System :: Systems Administration
Requires-Python: >=3.7, <3.9
Requires-Dist: atomicwrites (<2,>=1.4.0)
Requires-Dist: boto3 (<2,>=1.14.18)
Requires-Dist: click (<8,>=7.1.2)
Requires-Dist: click-log (<1,>=0.3.2)
Requires-Dist: fastavro (<1,>=0.23.5)
Requires-Dist: filelock (<4,>=3.0.12)
Requires-Dist: implements (<1,>=0.2.0)
Requires-Dist: pynacl (<2,>=1.4.0)
Requires-Dist: python-dynamodb-lock (<1,>=0.9.1)
